{
    "name": "Sonyliv Live Matches Data in Json",
    "telegram": "https://t.me/+rQTz5VL8CRpjNTZl",
    "last update time": "18:36:51 24-11-2024",
    "matches": [
        {
            "event_category": "Football",
            "isLive": true,
            "contentId": 1000297899,
            "src": "https://origin-staticv2.sonyliv.com/videoasset_images/football_24x7_19nov_landscape_thumb.jpg",
            "broadcast_channel": "LIV",
            "audioLanguageName": "ENG",
            "event_name": "Football Blockbusters 24x7",
            "match_name": ""
        },
        {
            "event_category": "Tennis",
            "isLive": false,
            "contentId": 1000295456,
            "src": "https://origin-staticv2.sonyliv.com/videoasset_images/daviscup_28oct_promo_landscape_thumb.jpg",
            "broadcast_channel": "Sony Sports Ten 2",
            "audioLanguageName": "ENG",
            "event_name": "Upcoming - Davis Cup 2024"
        },
        {
            "event_category": "Football",
            "isLive": false,
            "contentId": 1000297799,
            "src": "https://origin-staticv2.sonyliv.com/videoasset_images/bayern_vs_psg_27_nov_promo_landscape_thumb.jpg",
            "broadcast_channel": "Sony Sports Ten 5",
            "audioLanguageName": "ENG",
            "event_name": "Upcoming - Bayern Munich vs PSG - UEFA Champions League 2024-25"
        },
        {
            "event_category": "Football",
            "isLive": false,
            "contentId": 1000297802,
            "src": "https://origin-staticv2.sonyliv.com/videoasset_images/liverpool_vs_real_madrid_28_nov_promo_landscape_thumb.jpg",
            "broadcast_channel": "Sony Sports Ten 5",
            "audioLanguageName": "ENG",
            "event_name": "Upcoming - Liverpool vs Real Madrid - UEFA Champions League 2024-25"
        },
        {
            "event_category": "Football",
            "isLive": false,
            "contentId": 1000297797,
            "src": "https://origin-staticv2.sonyliv.com/videoasset_images/bayern_vs_psg_27_nov_promo_landscape_thumb.jpg",
            "broadcast_channel": "Sony Sports Ten 5",
            "audioLanguageName": "ENG",
            "event_name": "Upcoming - UEFA Champions League 2024-25 - 27th Nov 2024"
        }
    ]
}