{
    "name": "Sonyliv Live Matches Data in Json",
    "telegram": "https://t.me/+rQTz5VL8CRpjNTZl",
    "last update time": "19:32:55 02-03-2025",
    "matches": [
        {
            "event_category": "Football",
            "isLive": true,
            "contentId": 1090469762,
            "src": "https://origin-staticv2.sonyliv.com/videoasset_images/fa25_rd5_newcastleunited_vs_brighton_landscape_thumb.jpg",
            "broadcast_channel": "Sony Sports Ten 1",
            "audioLanguageName": "ENG",
            "event_name": "The Emirates FA Cup 2024-25",
            "match_name": "Newcastle United vs Brighton & Hove Albion - 2 Mar 2025",
            "dai_url": "https://dai.google.com/ssai/event/wN0bVs8wS9-yv6vL9G-tGQ/master.m3u8",
            "pub_url": "https://pubads.g.doubleclick.net/ssai/event/wN0bVs8wS9-yv6vL9G-tGQ/master.m3u8",
            "video_url": "https://sonydaimenew.akamaized.net/hls/live/2022320/DAI16ME-V3/master_mdh.m3u8?hdnea=exp=1740967374~acl=/*~id=15621490485801540492346602727215~hmac=ab6a81b2122ced03618e51f541765814379e58ba8ef5115a92fdd305f4ebe49e"
        },
        {
            "event_category": "Football",
            "isLive": true,
            "contentId": 1090469765,
            "src": "https://origin-staticv2.sonyliv.com/videoasset_images/bundesliga_md24_unionberlin_vs_holsteinkiel_landscape_thumb.jpg",
            "broadcast_channel": "Sony Sports Ten 2",
            "audioLanguageName": "ENG",
            "event_name": "Bundesliga 2024-25",
            "match_name": "Union Berlin vs Holstein Kiel - MD 24 - 2 Mar 2025",
            "dai_url": "https://sonyliveevents-nonssaime.akamaized.net/hls/live/2002929/LIV02UEFA/master_mdh.m3u8?hdnea=exp=1740967374~acl=/*~id=15621490485801540492346602727215~hmac=ab6a81b2122ced03618e51f541765814379e58ba8ef5115a92fdd305f4ebe49e",
            "pub_url": "https://sonyliveevents-nonssaime.akamaized.net/hls/live/2002929/LIV02UEFA/master_mdh.m3u8?hdnea=exp=1740967374~acl=/*~id=15621490485801540492346602727215~hmac=ab6a81b2122ced03618e51f541765814379e58ba8ef5115a92fdd305f4ebe49e",
            "video_url": "https://sonyliveevents-nonssaime.akamaized.net/hls/live/2002929/LIV02UEFA/master_mdh.m3u8?hdnea=exp=1740967374~acl=/*~id=15621490485801540492346602727215~hmac=ab6a81b2122ced03618e51f541765814379e58ba8ef5115a92fdd305f4ebe49e"
        },
        {
            "event_category": "Football",
            "isLive": false,
            "contentId": 1090469629,
            "src": "https://origin-staticv2.sonyliv.com/videoasset_images/man_united_vs_fulham_2nd_mar_landscape.jpg",
            "broadcast_channel": "Sony Sports Ten 5",
            "audioLanguageName": "ENG",
            "event_name": "Upcoming - Man United vs\u00a0Fulham -The Emirates FA Cup 2024-25"
        },
        {
            "event_category": "Football",
            "isLive": false,
            "contentId": 1090469646,
            "src": "https://origin-staticv2.sonyliv.com/videoasset_images/real_madrid_vs_atletico_madrid_5th_mar_landscape.jpg",
            "broadcast_channel": "Sony Sports Ten 5",
            "audioLanguageName": "ENG",
            "event_name": "Upcoming - Real Madrid vs Atletico Madrid - UEFA Champions League 2024-25"
        },
        {
            "event_category": "Football",
            "isLive": false,
            "contentId": 1090469650,
            "src": "https://origin-staticv2.sonyliv.com/videoasset_images/psg_vs_liverpool_6th_mar_landscape.jpg",
            "broadcast_channel": "Sony Sports Ten 5",
            "audioLanguageName": "ENG",
            "event_name": "Upcoming - PSG vs Liverpool - UEFA Champions League 2024-25"
        },
        {
            "event_category": "Football",
            "isLive": false,
            "contentId": 1090469630,
            "src": "https://origin-staticv2.sonyliv.com/videoasset_images/nottom_forrest_vs_ipswich_town_4th_mar_landscape.jpg",
            "broadcast_channel": "Sony Sports Ten 5",
            "audioLanguageName": "ENG",
            "event_name": "Upcoming - Nottingham Forest vs\u00a0Ipswich Town -The Emirates FA Cup 2024-25"
        },
        {
            "event_category": "Football",
            "isLive": false,
            "contentId": 1090469651,
            "src": "https://origin-staticv2.sonyliv.com/videoasset_images/benfica_vs_barcelona_6th_mar_landscape.jpg",
            "broadcast_channel": "Sony Sports Ten 5",
            "audioLanguageName": "ENG",
            "event_name": "Upcoming - Benfica vs Barcelona - UEFA Champions League 2024-25"
        },
        {
            "event_category": "Football",
            "isLive": false,
            "contentId": 1090469652,
            "src": "https://origin-staticv2.sonyliv.com/videoasset_images/bayern_vs_leverkusen_6th_mar_landscape.jpg",
            "broadcast_channel": "Sony Sports Ten 5",
            "audioLanguageName": "ENG",
            "event_name": "Upcoming - Bayern Munich vs Leverkusen - UEFA Champions League 2024-25"
        },
        {
            "event_category": "Football",
            "isLive": false,
            "contentId": 1090469647,
            "src": "https://origin-staticv2.sonyliv.com/videoasset_images/psv_vs_arsenal_5th_mar_landscape.jpg",
            "broadcast_channel": "Sony Sports Ten 5",
            "audioLanguageName": "ENG",
            "event_name": "Upcoming - PSV vs Arsenal - UEFA Champions League 2024-25"
        },
        {
            "event_category": "Football",
            "isLive": false,
            "contentId": 1090469649,
            "src": "https://origin-staticv2.sonyliv.com/videoasset_images/feyenoord_vs_inter_milan_5th_mar_landscape.jpg",
            "broadcast_channel": "Sony Sports Ten 5",
            "audioLanguageName": "ENG",
            "event_name": "Upcoming - Feyenoord vs Inter - UEFA Champions League 2024-25"
        },
        {
            "event_category": "Football",
            "isLive": false,
            "contentId": 1090469648,
            "src": "https://origin-staticv2.sonyliv.com/videoasset_images/dortmund_vs_losc_5th_mar_landscape.jpg",
            "broadcast_channel": "Sony Sports Ten 5",
            "audioLanguageName": "ENG",
            "event_name": "Upcoming - Dortmund vs LOSC - UEFA Champions League 2024-25"
        },
        {
            "event_category": "Football",
            "isLive": false,
            "contentId": 1090469645,
            "src": "https://origin-staticv2.sonyliv.com/videoasset_images/club_brugge_vs_aston_villa_4th_mar_landscape.jpg",
            "broadcast_channel": "Sony Sports Ten 5",
            "audioLanguageName": "ENG",
            "event_name": "Upcoming - Club Brugge vs Aston Villa - UEFA Champions League 2024-25"
        },
        {
            "event_category": "Cricket",
            "isLive": false,
            "contentId": 1090466414,
            "src": "https://origin-staticv2.sonyliv.com/videoasset_images/england_vs_india_promo_landscape.jpg",
            "broadcast_channel": "Sony Sports Ten 5",
            "audioLanguageName": "HIN",
            "event_name": "Upcoming - India Tour of England 2025"
        },
        {
            "event_category": "Cricket",
            "isLive": false,
            "contentId": 1090431389,
            "src": "https://origin-staticv2.sonyliv.com/videoasset_images/asia_cup_25022025_landscape.jpg",
            "broadcast_channel": "Sony Sports Ten 5",
            "audioLanguageName": "ENG",
            "event_name": "Upcoming - Asia Cup 2025"
        }
    ]
}