{
    "name": "Sonyliv Live Matches Data in Json",
    "telegram": "https://t.me/+rQTz5VL8CRpjNTZl",
    "last update time": "20:09:23 14-03-2025",
    "matches": [
        {
            "event_category": "Football",
            "isLive": false,
            "contentId": 1090473621,
            "src": "https://origin-staticv2.sonyliv.com/videoasset_images/manage_file/1000000260/1741769391865243_PROMO_RSL_AL_NASSR_vs_Al_Kholood_30_SEC_H_APP_Landscape_thumb.jpg",
            "broadcast_channel": "Sony Sports Ten 2",
            "audioLanguageName": "ENG",
            "event_name": "Upcoming - Al-Nassr vs Al-Kholood - Roshn Saudi League 2024-25"
        },
        {
            "event_category": "Football",
            "isLive": false,
            "contentId": 1090472589,
            "src": "https://origin-staticv2.sonyliv.com/videoasset_images/manage_file/1000000213/1741691227465266_UnionBerlin_vs_BayernMunich_15thMar_prom_Landscape_thumb.jpg",
            "broadcast_channel": "Sony Sports Ten 5",
            "audioLanguageName": "ENG",
            "event_name": "Upcoming - Union Berlin vs Bayern Munich"
        },
        {
            "event_category": "Football",
            "isLive": false,
            "contentId": 1090472603,
            "src": "https://origin-staticv2.sonyliv.com/videoasset_images/manage_file/1000000213/1741691256235266_Leipzig_vs_Dortmund_15thMar_prom_Landscape_thumb.jpg",
            "broadcast_channel": "Sony Sports Ten 5",
            "audioLanguageName": "ENG",
            "event_name": "Upcoming - RB Leipzig vs Borussia Dortmund"
        },
        {
            "event_category": "Football",
            "isLive": false,
            "contentId": 1090472604,
            "src": "https://origin-staticv2.sonyliv.com/videoasset_images/manage_file/1000000213/1741691337502266_Stuttgart_vs_Leverkusen_15thMar_prom_Landscape_thumb.jpg",
            "broadcast_channel": "Sony Sports Ten 5",
            "audioLanguageName": "ENG",
            "event_name": "Upcoming - VfB Stuttgart vs Bayer Leverkusen"
        }
    ]
}