{
    "name": "Sonyliv Live Matches Data in Json",
    "telegram": "https://t.me/+rQTz5VL8CRpjNTZl",
    "last update time": "10:39:48 21-09-2025",
    "matches": [
        {
            "event_category": "Tennis",
            "isLive": true,
            "contentId": "1090490082_ENG",
            "src": "https://origin-staticv2.sonyliv.com/videoasset_images/manage_file/1000008840/175827246915869_LaverCup25_Day2_S2_Live_Landscape_thumb.jpg",
            "broadcast_channel": "Sony Sports Ten 5",
            "audioLanguageName": "ENG",
            "event_name": "Laver Cup 2025",
            "match_name": "Day 2 - Session 2 - 21 Sep 2025 [ENG]",
            "dai_url": "https://liveakdai.slivcdn.com/hls/live/2118980/Laver_Cu2109/ENG/std_lrh-800300010.m3u8?hdnea=exp=1758474588~acl=/*~id=66771253451730366374205129363158~hmac=90353bac81c3844559eefa204901448c52058968117b54e36018e2885086ec18",
            "pub_url": "https://liveakdai.slivcdn.com/hls/live/2118980/Laver_Cu2109/ENG/std_lrh-800300010.m3u8?hdnea=exp=1758474588~acl=/*~id=66771253451730366374205129363158~hmac=90353bac81c3844559eefa204901448c52058968117b54e36018e2885086ec18",
            "video_url": "https://liveakdai.slivcdn.com/hls/live/2118980/Laver_Cu2109/ENG/std_lrh-800300010.m3u8?hdnea=exp=1758474588~acl=/*~id=66771253451730366374205129363158~hmac=90353bac81c3844559eefa204901448c52058968117b54e36018e2885086ec18"
        },
        {
            "event_category": "Cricket",
            "isLive": false,
            "contentId": 1090489988,
            "src": "https://origin-staticv2.sonyliv.com/videoasset_images/manage_file/1000009011/1758397041064640_ACC_rail1_INDvsPAK_promo1_landscape_thumb.jpg",
            "broadcast_channel": "Sony Sports Ten 5",
            "audioLanguageName": "HIN",
            "event_name": "Upcoming - India vs Pakistan - Super 4 - Asia Cup 2025"
        },
        {
            "event_category": "Cricket",
            "isLive": false,
            "contentId": 1090490287,
            "src": "https://origin-staticv2.sonyliv.com/videoasset_images/manage_file/1000008871/1758295323373630_ACC25_IND_VS_BAN_S4_dated_19sep_promo_rev_LANDCAPE_thumb.jpg",
            "broadcast_channel": "Sony Sports Ten 5",
            "audioLanguageName": "HIN",
            "event_name": "Upcoming - India vs Bangladesh - Super 4 - Asia Cup 2025"
        },
        {
            "event_category": "Cricket",
            "isLive": false,
            "contentId": 1090490288,
            "src": "https://origin-staticv2.sonyliv.com/videoasset_images/manage_file/1000008871/1758295218050630_ACC25_PAK_vs_SL_S4_DATED_19sep_rev_promo_landscape_thumb.jpg",
            "broadcast_channel": "Sony Sports Ten 5",
            "audioLanguageName": "HIN",
            "event_name": "Upcoming - Pakistan vs Sri Lanka - Super 4 - Asia Cup 2025"
        },
        {
            "event_category": "Cricket",
            "isLive": false,
            "contentId": 1090489002,
            "src": "https://origin-staticv2.sonyliv.com/videoasset_images/manage_file/1000008092/1757691706791589_SPORTS_COMBO_PROMO_landscape.jpg",
            "broadcast_channel": "Sony Sports Ten 5",
            "audioLanguageName": "ENG",
            "event_name": "Upcoming - The Best Sporting Action"
        },
        {
            "event_category": "Tennis",
            "isLive": false,
            "contentId": 1090489959,
            "src": "https://origin-staticv2.sonyliv.com/videoasset_images/manage_file/1000008731/1758191270258475_Laver_cup_Team_Europe_vs_Team_World_landscape_thumb.jpg",
            "broadcast_channel": "Sony Sports Ten 5",
            "audioLanguageName": "ENG",
            "event_name": "Upcoming - Laver Cup 2025"
        },
        {
            "event_category": "Cricket",
            "isLive": false,
            "contentId": 1090487792,
            "src": "https://origin-staticv2.sonyliv.com/videoasset_images/manage_file/1000008900/1758304754759139_ACC25_dated_19sep_generic_landscape.jpg",
            "broadcast_channel": "Sony Sports Ten 5",
            "audioLanguageName": "HIN",
            "event_name": "Upcoming - Asia Cup 2025"
        },
        {
            "event_category": "Cricket",
            "isLive": false,
            "contentId": 1090490157,
            "src": "https://origin-staticv2.sonyliv.com/videoasset_images/manage_file/1000008906/1758307276841169_PROMO_SUPER_4_COMBO_PROMO__landscape_thumb.jpg",
            "broadcast_channel": "Sony Sports Ten 5",
            "audioLanguageName": "HIN",
            "event_name": "Upcoming - Super 4 - Asia Cup 2025"
        }
    ]
}