{
  "name": "Sonyliv Live Matches Data in Json",
  "telegram": "https://t.me/+rQTz5VL8CRpjNTZl",
  "last update time": "15:37:39 11-09-2024",
  "matches": [
    {
      "event_category": "hockey",
      "event_name": "men s asian champions trophy 2024",
      "match_name": "china vs korea 11 sep 2024",
      "src": "https://origin-staticv2.sonyliv.com/videoasset_images/hact_china_vs_korea_10sep_landscape_thumb.jpg",
      "match_id": "1000290651",
      "dai_stream_url": "https://dai.google.com/ssai/event/8cov9tHQRj26xm-Qz6uWzQ/master.m3u8",
      "pub_stream_url": "https://pubads.g.doubleclick.net/ssai/event/8cov9tHQRj26xm-Qz6uWzQ/master.m3u8"
    },
    {
      "event_category": "tennis",
      "event_name": "davis cup 2024",
      "match_name": "usa vs chile 11 sep 2024",
      "src": "https://origin-staticv2.sonyliv.com/videoasset_images/davis_cup_usa_vs_chile_live_10_sep_24_landscape_thumb.jpg",
      "match_id": "1000290668",
      "dai_stream_url": "https://dai.google.com/ssai/event/jirIBSMoQDWBeTr-f6WNpA/master.m3u8",
      "pub_stream_url": "https://pubads.g.doubleclick.net/ssai/event/jirIBSMoQDWBeTr-f6WNpA/master.m3u8"
    }
  ]
}