{
    "name": "Sonyliv Live Matches Data in Json",
    "telegram": "https://t.me/+rQTz5VL8CRpjNTZl",
    "last update time": "00:21:31 26-10-2024",
    "matches": [
        {
            "event_category": "Football",
            "isLive": true,
            "contentId": 1000295187,
            "src": "https://origin-staticv2.sonyliv.com/videoasset_images/spl2425_md8_al_ahli_vs_al_okhdood_25oct_landscape_thumb.jpg",
            "broadcast_channel": "Sony Sports Ten 2",
            "audioLanguageName": "ENG",
            "event_name": "Roshn Saudi League 2024-25",
            "match_name": "Al Ahli vs Al Okhdood - MD 8 - 25 Oct 2024",
            "dai_url": "https://dai.google.com/ssai/event/QNEZiPzpTXucyrbpCjdZTw/master.m3u8",
            "pub_url": "https://pubads.g.doubleclick.net/ssai/event/QNEZiPzpTXucyrbpCjdZTw/master.m3u8",
            "video_url": "https://sonydaimenew.akamaized.net/hls/live/2105080/DAI24ME-V3/master_mdh.m3u8?hdnea=exp=1729914991~acl=*~id=1556784483112233~hmac=c2ec6a57c55154004dd1d0b2b9f9f096a062cfb6872c2a6c93fcfa8af14fc521"
        },
        {
            "event_category": "Football",
            "isLive": true,
            "contentId": 1000295221,
            "src": "https://origin-staticv2.sonyliv.com/videoasset_images/bliga2425_md8_mainz_vs_borussia_25oct_landscape_thumb.jpg",
            "broadcast_channel": "Sony Sports Ten 2",
            "audioLanguageName": "ENG",
            "event_name": "Bundesliga 2024-25",
            "match_name": "Mainz vs Borussia M'gladbach - MD 8 - 26 Oct 2024",
            "dai_url": "https://sonyliveevents-nonssaime.akamaized.net/hls/live/2002930/LIV03UEFA/master_mdh.m3u8?hdnea=exp=1729914991~acl=*~id=1556784483112233~hmac=c2ec6a57c55154004dd1d0b2b9f9f096a062cfb6872c2a6c93fcfa8af14fc521",
            "pub_url": "https://sonyliveevents-nonssaime.akamaized.net/hls/live/2002930/LIV03UEFA/master_mdh.m3u8?hdnea=exp=1729914991~acl=*~id=1556784483112233~hmac=c2ec6a57c55154004dd1d0b2b9f9f096a062cfb6872c2a6c93fcfa8af14fc521",
            "video_url": "https://sonyliveevents-nonssaime.akamaized.net/hls/live/2002930/LIV03UEFA/master_mdh.m3u8?hdnea=exp=1729914991~acl=*~id=1556784483112233~hmac=c2ec6a57c55154004dd1d0b2b9f9f096a062cfb6872c2a6c93fcfa8af14fc521"
        },
        {
            "event_category": "Table Tennis",
            "isLive": true,
            "contentId": 1000295149,
            "src": "https://origin-staticv2.sonyliv.com/videoasset_images/wtt_day4_s2_23oct_landscape_thumb.jpg",
            "broadcast_channel": "LIV",
            "audioLanguageName": "ENG",
            "event_name": "WTT Champions Montpellier 2024",
            "match_name": "Day 4 - Session 2 - 25 Oct 2024",
            "dai_url": "https://sonyliveevents-nonssaime.akamaized.net/hls/live/2002929/LIV02UEFA/master_mdh.m3u8?hdnea=exp=1729914991~acl=*~id=1556784483112233~hmac=c2ec6a57c55154004dd1d0b2b9f9f096a062cfb6872c2a6c93fcfa8af14fc521",
            "pub_url": "https://sonyliveevents-nonssaime.akamaized.net/hls/live/2002929/LIV02UEFA/master_mdh.m3u8?hdnea=exp=1729914991~acl=*~id=1556784483112233~hmac=c2ec6a57c55154004dd1d0b2b9f9f096a062cfb6872c2a6c93fcfa8af14fc521",
            "video_url": "https://sonyliveevents-nonssaime.akamaized.net/hls/live/2002929/LIV02UEFA/master_mdh.m3u8?hdnea=exp=1729914991~acl=*~id=1556784483112233~hmac=c2ec6a57c55154004dd1d0b2b9f9f096a062cfb6872c2a6c93fcfa8af14fc521"
        },
        {
            "event_category": "Cricket",
            "isLive": false,
            "contentId": 1000293773,
            "src": "https://origin-staticv2.sonyliv.com/videoasset_images/promo_sri_lanka_vs_west_indies_landscape_thumb.jpg",
            "broadcast_channel": "Sony Sports Ten 5",
            "audioLanguageName": "ENG",
            "event_name": "Upcoming - West Indies Tour of Sri Lanka 2024"
        },
        {
            "event_category": "Football",
            "isLive": false,
            "contentId": 1000295217,
            "src": "https://origin-staticv2.sonyliv.com/videoasset_images/bliga_promo_augsburg_v_dortmund_landscape_thumb.jpg",
            "broadcast_channel": "Sony Sports Ten 2",
            "audioLanguageName": "ENG",
            "event_name": "Upcoming - FC Augsburg vs Borussia Dortmund"
        },
        {
            "event_category": "Football",
            "isLive": false,
            "contentId": 1000295219,
            "src": "https://origin-staticv2.sonyliv.com/videoasset_images/bliga_promo_bochum_v_bayern_landscape_thumb.jpg",
            "broadcast_channel": "Sony Sports Ten 2",
            "audioLanguageName": "ENG",
            "event_name": "Upcoming - VfL Bochum vs Bayern Munich"
        }
    ]
}